hackforall77/__init__.py
hackforall77/courses.py
hackforall77/utils.py
hackforall77-0.0.1.dist-info/METADATA
hackforall77-0.0.1.dist-info/WHEEL
hackforall77-0.0.1.dist-info/top_level.txt
hackforall77-0.0.1.dist-info/RECORD
